jsonschema_to_openapi/__init__.py
jsonschema_to_openapi/__main__.py
jsonschema_to_openapi/cli.py
jsonschema_to_openapi/convert.py
jsonschema_to_openapi/exceptions.py
jsonschema_to_openapi/utils/__init__.py
jsonschema_to_openapi/utils/io.py
jsonschema_to_openapi/utils/logger.py
jsonschema_to_openapi-0.2.1.dist-info/entry_points.txt
jsonschema_to_openapi-0.2.1.dist-info/LICENSE
jsonschema_to_openapi-0.2.1.dist-info/WHEEL
jsonschema_to_openapi-0.2.1.dist-info/METADATA
jsonschema_to_openapi-0.2.1.dist-info/RECORD
