Metadata-Version: 2.1
Name: jsonschema-to-openapi
Version: 0.2.1
Summary: Converts a JSON schema to an OpenAPI specification version 3.0.
Home-page: https://instaffo.com
Author: Instaffo GmbH
Author-email: info@instaffo.de
Requires-Python: >=3.6,<4.0
Classifier: Programming Language :: Python :: 3
Classifier: Programming Language :: Python :: 3.6
Classifier: Programming Language :: Python :: 3.7
Classifier: Programming Language :: Python :: 3.8
Requires-Dist: jsonschema (>=3.2.0,<4.0.0)
Project-URL: Repository, https://gitlab.com/InstaffoOpenSource/DataScience/jsonschema-to-openapi
